dirhash/__init__.py
dirhash/_version.py
dirhash/cli.py
dirhash-0.4.1.dist-info/LICENSE
dirhash-0.4.1.dist-info/METADATA
dirhash-0.4.1.dist-info/WHEEL
dirhash-0.4.1.dist-info/entry_points.txt
dirhash-0.4.1.dist-info/top_level.txt
dirhash-0.4.1.dist-info/RECORD
