Metadata-Version: 2.1
Name: dirhash
Version: 0.4.1
Summary: Python module and CLI for hashing of file system directories.
Home-page: https://github.com/andhus/dirhash-python
Author: Anders Huss
Author-email: andhus@kth.se
License: MIT
Requires-Python: >=3.8
License-File: LICENSE
Requires-Dist: scantree
